{
    "breadcrumbs.enabled": false,
    "editor.folding": false,
    "editor.fontFamily": "Source Code Pro",
    "editor.fontSize": 16,
    "editor.lineHeight": 1.5,
    "editor.minimap.enabled": false,
    "editor.rulers": [
        120
    ],
    "emmet.showExpandedAbbreviation": "never",
    "explorer.confirmDelete": false,
    "files.insertFinalNewline": true,
    "files.trimFinalNewlines": true,
    "files.trimTrailingWhitespace": true,
    "javascript.format.insertSpaceAfterOpeningAndBeforeClosingEmptyBraces": false,
    "javascript.format.insertSpaceAfterOpeningAndBeforeClosingNonemptyBraces": false,
    "javascript.preferences.importModuleSpecifierEnding": "js",
    "telemetry.telemetryLevel": "off",
    "volar.completion.autoImportComponent": false,
    "workbench.editor.restoreViewState": false,
    "workbench.enableExperiments": false,
    "workbench.tree.indent": 12
}
